pyhoster/__init__.py
pyhoster/main.py
pyhoster-1.1.0.data/data/share/man/man8/pyhoster.8
pyhoster-1.1.0.dist-info/licenses/LICENSE
pyserve/__init__.py
pyserve/main.py
pyhoster-1.1.0.dist-info/METADATA
pyhoster-1.1.0.dist-info/WHEEL
pyhoster-1.1.0.dist-info/entry_points.txt
pyhoster-1.1.0.dist-info/top_level.txt
pyhoster-1.1.0.dist-info/RECORD
