Metadata-Version: 2.4
Name: pyhoster
Version: 1.1.0
Summary: A simple tool for servers that host python projects
Home-page: https://github.com/mbutsk/pyhoster
Author: mbutsk
Author-email: mbutsk@icloud.com
License: MIT License, see LICENSE.md file
Keywords: cli,server,process,manager,console,script
Classifier: License :: OSI Approved :: MIT License
Classifier: Topic :: System :: Systems Administration
Classifier: Topic :: Utilities
Classifier: Programming Language :: Python
Classifier: Operating System :: Unix
Classifier: Intended Audience :: System Administrators
License-File: LICENSE
Dynamic: author
Dynamic: author-email
Dynamic: classifier
Dynamic: description
Dynamic: description-content-type
Dynamic: home-page
Dynamic: keywords
Dynamic: license
Dynamic: license-file
Dynamic: summary
